eopayment/__init__.py
eopayment/__main__.py
eopayment/cb.py
eopayment/common.py
eopayment/dummy.py
eopayment/keyware.py
eopayment/mollie.py
eopayment/ogone.py
eopayment/paybox.py
eopayment/payfip_ws.py
eopayment/payzen.py
eopayment/response
eopayment/saga.py
eopayment/sips2.py
eopayment/systempayv2.py
eopayment/tipi.py
eopayment/worldline.py
eopayment/locale/fr/LC_MESSAGES/django.po
eopayment/resource/PaiementSecuriseService.wsdl
eopayment/resource/PaiementSecuriseService_schema1.xsd
eopayment/resource/PaiementSecuriseService_schema2.xsd
eopayment/resource/PaiementSecuriseService_schema3.xsd
eopayment-3.7.dist-info/COPYING
eopayment-3.7.dist-info/METADATA
eopayment-3.7.dist-info/WHEEL
eopayment-3.7.dist-info/top_level.txt
eopayment-3.7.dist-info/RECORD
