Metadata-Version: 2.2
Name: eopayment
Version: 3.7
Summary: Common API to use all French online payment credit card processing services
Home-page: http://dev.entrouvert.org/projects/eopayment/
Author: Entr'ouvert
Author-email: info@entrouvert.com
Maintainer: Benjamin Dauvergne
Maintainer-email: bdauvergne@entrouvert.com
License: GPLv3 or later
Classifier: Development Status :: 5 - Production/Stable
Classifier: Environment :: Web Environment
Classifier: Intended Audience :: Developers
Classifier: License :: OSI Approved :: GNU General Public License v3 or later (GPLv3+)
Classifier: Operating System :: POSIX
Classifier: Programming Language :: Python
Classifier: Programming Language :: Python :: 3
License-File: COPYING
Requires-Dist: pycryptodomex
Requires-Dist: pytz
Requires-Dist: requests
Requires-Dist: click
Requires-Dist: zeep>=2.5
Dynamic: author
Dynamic: author-email
Dynamic: classifier
Dynamic: description
Dynamic: description-content-type
Dynamic: home-page
Dynamic: license
Dynamic: maintainer
Dynamic: maintainer-email
Dynamic: requires-dist
Dynamic: summary
